brocket/__init__.py
brocket/__main__.py
brocket-1.2.dist-info/METADATA
brocket-1.2.dist-info/RECORD
brocket-1.2.dist-info/WHEEL
brocket-1.2.dist-info/entry_points.txt
brocket-1.2.dist-info/top_level.txt
