Metadata-Version: 2.1
Name: brocket
Version: 1.2
Summary: Build Amazon Associates Links in the clipboard super fast.
Home-page: http://github.com/jachin/brocket
Author: Jachin Rupe
Author-email: jachin@jachin.rupe.name
License: MIT
Platform: UNKNOWN
Classifier: Development Status :: 5 - Production/Stable
Classifier: License :: OSI Approved :: MIT License
Classifier: Programming Language :: Python :: 3.5
Classifier: Topic :: Utilities
Classifier: Intended Audience :: End Users/Desktop
Classifier: Environment :: MacOS X
Requires-Dist: urlobject
Requires-Dist: pyperclip
